gen_pygments_css/__init__.py
gen_pygments_css/__main__.py
gen_pygments_css/gen_pygments_css.py
gen_pygments_css-0.0.3.dist-info/LICENSE
gen_pygments_css-0.0.3.dist-info/LICENSE.txt
gen_pygments_css-0.0.3.dist-info/METADATA
gen_pygments_css-0.0.3.dist-info/WHEEL
gen_pygments_css-0.0.3.dist-info/entry_points.txt
gen_pygments_css-0.0.3.dist-info/top_level.txt
gen_pygments_css-0.0.3.dist-info/RECORD
