Metadata-Version: 2.1
Name: gen-pygments-css
Version: 0.0.3
Summary: Generate CSS stylesheets for each Pygments supported style.
Home-page: https://github.com/hreikin/gen-pygments-css
Author: hreikin
Author-email: hreikin@gmail.com
License: MIT
Platform: UNKNOWN
Classifier: License :: OSI Approved :: MIT License
Classifier: Programming Language :: Python :: 3
Classifier: Programming Language :: Python :: 3.7
License-File: LICENSE
License-File: LICENSE.txt
Requires-Dist: pygments
